roc_utils/__init__.py
roc_utils/_demo.py
roc_utils/_plot.py
roc_utils/_roc.py
roc_utils/_sampling.py
roc_utils/_stats.py
roc_utils/_types.py
roc_utils-0.2.2.dist-info/LICENSE
roc_utils-0.2.2.dist-info/METADATA
roc_utils-0.2.2.dist-info/WHEEL
roc_utils-0.2.2.dist-info/top_level.txt
roc_utils-0.2.2.dist-info/RECORD
