Metadata-Version: 2.1
Name: roc-utils
Version: 0.2.2
Summary: Tools to compute and visualize ROC curves.
Home-page: https://github.com/hirsch-lab/roc-utils
Author: Norman Juchler
License: MIT
Keywords: ROC AUC receiver operating characteristic
Platform: UNKNOWN
Classifier: Programming Language :: Python :: 3
Classifier: License :: OSI Approved :: MIT License
Classifier: Operating System :: OS Independent
Classifier: Topic :: Scientific/Engineering :: Mathematics
Classifier: Topic :: Software Development :: Libraries
Classifier: Topic :: Utilities
Classifier: Intended Audience :: Developers
Classifier: Intended Audience :: Science/Research
Requires-Python: >=3.6
Requires-Dist: numpy
Requires-Dist: scipy
Requires-Dist: pandas
Requires-Dist: matplotlib
